riotmanifest/__init__.py
riotmanifest/external_manifest.py
riotmanifest/extractor.py
riotmanifest/game.py
riotmanifest/native_manifest.py
riotmanifest-1.1.0.dist-info/METADATA
riotmanifest-1.1.0.dist-info/WHEEL
riotmanifest-1.1.0.dist-info/licenses/LICENSE
riotmanifest-1.1.0.dist-info/RECORD
