Metadata-Version: 2.3
Name: riotmanifest
Version: 1.1.0
Summary: Add your description here
Author-email: Virace <Virace@aliyun.com>
License-Expression: GPL-3.0
License-File: LICENSE
Requires-Python: >=3.8
Requires-Dist: aiohttp>=3.10.5
Requires-Dist: league-tools>=0.2.3
Requires-Dist: loguru>=0.7.2
Requires-Dist: pyzstd>=0.16.1
Requires-Dist: requests>=2.32.3
